automathon/__init__.py
automathon/__version__.py
automathon/errors/__init__.py
automathon/errors/errors.py
automathon/finiteAutomata/__init__.py
automathon/finiteAutomata/dfa.py
automathon/finiteAutomata/nfa.py
automathon-0.0.15.dist-info/LICENSE
automathon-0.0.15.dist-info/METADATA
automathon-0.0.15.dist-info/WHEEL
automathon-0.0.15.dist-info/top_level.txt
automathon-0.0.15.dist-info/RECORD
