Metadata-Version: 2.1
Name: automathon
Version: 0.0.15
Summary: A Python library for simulating and visualizing finite automata
Home-page: https://github.com/rohaquinlop/automathon
Download-URL: https://github.com/rohaquinlop/automathon/archive/refs/tags/v0.0.15.tar.gz
Author: Robin Hafid Quintero Lopez
Author-email: rohaquinlop301@gmail.com
License: MIT
Keywords: python,automata,automata,automathon
Classifier: Development Status :: 3 - Alpha
Classifier: Intended Audience :: Developers
Classifier: Topic :: Software Development :: Build Tools
Classifier: License :: OSI Approved :: MIT License
Classifier: Programming Language :: Python :: 3
License-File: LICENSE
